README.md
setup.py
database/__init__.py
database/neo4j/__init__.py
database/neo4j/database_clients.py
database/neo4j/database_manager.py
graph_database_loader.egg-info/PKG-INFO
graph_database_loader.egg-info/SOURCES.txt
graph_database_loader.egg-info/dependency_links.txt
graph_database_loader.egg-info/not-zip-safe
graph_database_loader.egg-info/requires.txt
graph_database_loader.egg-info/top_level.txt
loader/__init__.py
loader/cleanup_neo4j.py
loader/load_all_in_parallel.py
loader/load_ancient_greek.py
loader/load_german.py
loader/load_italian.py
loader/load_latin.py
loader/loader.py
wiktionary_data/__init__.py
wiktionary_data/load_graph.py