Metadata-Version: 2.1
Name: graph-database-loader
Version: 0.0.52
Summary: A package suitable for offline vocabulary processing and batch ingestion into Graph databases, such as Neo4j and ArangoDB
Home-page: https://github.com/QubitPi/Antiqua/tree/master/graph-database-loader
Author: Jiaqi Liu
Author-email: jack20220723@gmail.com
License: Apache-2.0
Requires-Python: >=3.10
